LICENSE
MANIFEST.in
README.md
requirements.txt
setup.cfg
setup.py
gh_license.egg-info/PKG-INFO
gh_license.egg-info/PKG-INFO (conflicted copy 2019-10-28 103747)
gh_license.egg-info/SOURCES.txt
gh_license.egg-info/dependency_links.txt
gh_license.egg-info/entry_points.txt
gh_license.egg-info/requires.txt
gh_license.egg-info/top_level.txt
ghlicense/__init__.py
ghlicense/cmd.py
ghlicense/licenses.json
ghlicense/repobase.py
ghlicense/providers/__init__.py
ghlicense/providers/bitbucket.py
ghlicense/providers/github.py
ghlicense/providers/gitlab.py
setup/__init__.py
setup/setup_hook.py
setup/hooks/pre-commit.py