Metadata-Version: 2.1
Name: gh-license
Version: 0.3.0
Summary: Scan github, bitbucket or other providers repositories for missing license files and add them
Home-page: https://github.com/Mte90/GH-License
Download-URL: https://github.com/Mte90/GH-License/tarball/0.3.0
Author: Mte90
Author-email: mte90net@gmail.com
License: GPLv3
License-File: LICENSE
